avanza/__init__.py
avanza/_version.py
avanza/base.py
avanza/chartdata.py
avanza/collection.py
avanza/constants.py
avanza/news.py
avanza/search.py
avanza/ticker.py
Avanza-0.0.13.dist-info/LICENSE
Avanza-0.0.13.dist-info/METADATA
Avanza-0.0.13.dist-info/WHEEL
Avanza-0.0.13.dist-info/top_level.txt
Avanza-0.0.13.dist-info/RECORD
