Metadata-Version: 2.1
Name: Avanza
Version: 0.0.13
Summary: Python wrapper for Unofficial Avanza API
Home-page: https://github.com/North14/avanza
Author: North14
License: UNKNOWN
Platform: any
Classifier: License :: OSI Approved :: MIT License
Classifier: Operating System :: OS Independent
Classifier: Intended Audience :: Developers
Classifier: Programming Language :: Python :: 3
Classifier: Programming Language :: Python :: 3.6
Classifier: Programming Language :: Python :: 3.7
Classifier: Programming Language :: Python :: 3.8
Classifier: Topic :: Office/Business :: Financial
Classifier: Topic :: Office/Business :: Financial :: Investment
Requires-Python: >=3.6
Requires-Dist: requests
Requires-Dist: selenium
Requires-Dist: pandas
